{"SURVIVAL":{"offHandItem":{"==":"org.bukkit.inventory.ItemStack","v":2230,"type":"AIR","amount":0},"inventoryContents":{"37":{"==":"org.bukkit.inventory.ItemStack","v":2230,"type":"GOLDEN_LEGGINGS","meta":{"==":"ItemMeta","meta-type":"UNSPECIFIC","Damage":4}},"8":{"==":"org.bukkit.inventory.ItemStack","v":2230,"type":"CLOCK","meta":{"==":"ItemMeta","meta-type":"UNSPECIFIC","display-name":"§dМеню сервера"}}},"armorContents":{"1":{"==":"org.bukkit.inventory.ItemStack","v":2230,"type":"GOLDEN_LEGGINGS","meta":{"==":"ItemMeta","meta-type":"UNSPECIFIC","Damage":4}}},"potions":[],"enderChestContents":{},"stats":{"ex":"1.7740185","ma":"300","fl":"20","el":"7","xp":"0.4761906","hp":"20.0","txp":"101","sa":"0.0","fd":"0.0","ft":"-20","ra":"300"}}}